mw_api_parser/__init__.py
mw_api_parser/def_audio_links.py
mw_api_parser/get_def_html.py
mw_api_parser/get_def_original.py
mw_api_parser/get_def_plain_text.py
mw_api_parser/mw_api_response.py
mw_api_parser-1.0.1.dist-info/LICENSE.txt
mw_api_parser-1.0.1.dist-info/METADATA
mw_api_parser-1.0.1.dist-info/WHEEL
mw_api_parser-1.0.1.dist-info/top_level.txt
mw_api_parser-1.0.1.dist-info/RECORD
