Metadata-Version: 2.1
Name: mw-api-parser
Version: 1.0.1
Summary: Python wrapper to help parse the Merriam-Webster API response
Home-page: https://github.com/whitej27030/MW_API_Parser.git
Author: Jerry White
Author-email: MidwayVI@surry.net
Classifier: Programming Language :: Python :: 3
Classifier: License :: OSI Approved :: MIT License
Classifier: Operating System :: OS Independent
Requires-Python: >=3.11
License-File: LICENSE.txt
Requires-Dist: python-dotenv (>=0.21.0)
